tron_api/grpc/api/api_pb2.py
tron_api/grpc/api/api_pb2.pyi
tron_api/grpc/api/api_pb2_grpc.py
tron_api/grpc/core/Discover_pb2.py
tron_api/grpc/core/Discover_pb2.pyi
tron_api/grpc/core/Discover_pb2_grpc.py
tron_api/grpc/core/Tron_pb2.py
tron_api/grpc/core/Tron_pb2.pyi
tron_api/grpc/core/Tron_pb2_grpc.py
tron_api/grpc/core/contract/account_contract_pb2.py
tron_api/grpc/core/contract/account_contract_pb2.pyi
tron_api/grpc/core/contract/account_contract_pb2_grpc.py
tron_api/grpc/core/contract/asset_issue_contract_pb2.py
tron_api/grpc/core/contract/asset_issue_contract_pb2.pyi
tron_api/grpc/core/contract/asset_issue_contract_pb2_grpc.py
tron_api/grpc/core/contract/balance_contract_pb2.py
tron_api/grpc/core/contract/balance_contract_pb2.pyi
tron_api/grpc/core/contract/balance_contract_pb2_grpc.py
tron_api/grpc/core/contract/common_pb2.py
tron_api/grpc/core/contract/common_pb2.pyi
tron_api/grpc/core/contract/common_pb2_grpc.py
tron_api/grpc/core/contract/exchange_contract_pb2.py
tron_api/grpc/core/contract/exchange_contract_pb2.pyi
tron_api/grpc/core/contract/exchange_contract_pb2_grpc.py
tron_api/grpc/core/contract/market_contract_pb2.py
tron_api/grpc/core/contract/market_contract_pb2.pyi
tron_api/grpc/core/contract/market_contract_pb2_grpc.py
tron_api/grpc/core/contract/proposal_contract_pb2.py
tron_api/grpc/core/contract/proposal_contract_pb2.pyi
tron_api/grpc/core/contract/proposal_contract_pb2_grpc.py
tron_api/grpc/core/contract/shield_contract_pb2.py
tron_api/grpc/core/contract/shield_contract_pb2.pyi
tron_api/grpc/core/contract/shield_contract_pb2_grpc.py
tron_api/grpc/core/contract/smart_contract_pb2.py
tron_api/grpc/core/contract/smart_contract_pb2.pyi
tron_api/grpc/core/contract/smart_contract_pb2_grpc.py
tron_api/grpc/core/contract/storage_contract_pb2.py
tron_api/grpc/core/contract/storage_contract_pb2.pyi
tron_api/grpc/core/contract/storage_contract_pb2_grpc.py
tron_api/grpc/core/contract/vote_asset_contract_pb2.py
tron_api_python-0.1.0.dist-info/METADATA
tron_api_python-0.1.0.dist-info/WHEEL
tron_api_python-0.1.0.dist-info/RECORD
