Metadata-Version: 2.1
Name: tron-api-python
Version: 0.1.0
Summary: 
Author: Your Name
Author-email: you@example.com
Requires-Python: >=3.10,<4.0
Classifier: Programming Language :: Python :: 3
Classifier: Programming Language :: Python :: 3.10
Classifier: Programming Language :: Python :: 3.11
Classifier: Programming Language :: Python :: 3.12
Requires-Dist: base58 (>=2.1.1,<3.0.0)
Requires-Dist: ecdsa (>=0.18.0,<0.19.0)
Requires-Dist: grpcio-tools (>=1.60.0,<2.0.0)
Requires-Dist: pycryptodome (>=3.17,<4.0)
Requires-Dist: requests (>=2.31.0,<3.0.0)
